proofy/__init__.py
proofy/py.typed
proofy/_internal/__init__.py
proofy/_internal/config.py
proofy/_internal/constants.py
proofy/_internal/logging_scopes.py
proofy/_internal/artifacts/__init__.py
proofy/_internal/artifacts/attachments_cache.py
proofy/_internal/artifacts/models.py
proofy/_internal/artifacts/service.py
proofy/_internal/artifacts/uploader.py
proofy/_internal/context/__init__.py
proofy/_internal/context/backend.py
proofy/_internal/context/models.py
proofy/_internal/context/service.py
proofy/_internal/hooks/__init__.py
proofy/_internal/hooks/manager.py
proofy/_internal/hooks/specs.py
proofy/_internal/results/__init__.py
proofy/_internal/results/limits.py
proofy/_internal/results/publishers.py
proofy/_internal/results/result_buffer.py
proofy/_internal/results/result_handler.py
proofy/_internal/results/run_manager.py
proofy/_internal/results/utils.py
proofy/_internal/uploader/__init__.py
proofy/_internal/uploader/queue.py
proofy/_internal/uploader/worker.py
proofy/core/__init__.py
proofy/core/api.py
proofy/core/decorators.py
proofy/core/models.py
proofy/core/system_info.py
proofy/core/utils.py
proofy/core/client/__init__.py
proofy/core/client/async_client.py
proofy/core/client/base.py
proofy/core/client/sync_client.py
proofy_python-0.1.2.dist-info/METADATA
proofy_python-0.1.2.dist-info/WHEEL
proofy_python-0.1.2.dist-info/top_level.txt
proofy_python-0.1.2.dist-info/RECORD
