Metadata-Version: 2.4
Name: proofy-python
Version: 0.1.2
Summary: Shared components for Proofy Python testing framework integrations
Author-email: Proofy Team <team@proofy.dev>, Krzysztof Marmol <krzysztof.marmol@gmail.com>
License-Expression: Apache-2.0
Keywords: testing,proofy,commons,shared
Classifier: Development Status :: 4 - Beta
Classifier: Intended Audience :: Developers
Classifier: Programming Language :: Python
Classifier: Programming Language :: Python :: 3
Classifier: Programming Language :: Python :: 3.10
Classifier: Programming Language :: Python :: 3.12
Classifier: Topic :: Software Development :: Testing
Requires-Python: >=3.10
Requires-Dist: httpx>=0.27.0
Requires-Dist: pluggy>=0.13.1
Provides-Extra: dev
Requires-Dist: pytest>=8.2; extra == "dev"
Requires-Dist: pytest-asyncio>=0.23.0; extra == "dev"
Requires-Dist: pytest-xdist>=3.0; extra == "dev"
Requires-Dist: pytest-cov>=4.1; extra == "dev"
Requires-Dist: coverage[toml]>=7.0; extra == "dev"
Requires-Dist: mypy>=1.10; extra == "dev"
Requires-Dist: respx>=0.21.0; extra == "dev"
